ipyregulartable/__init__.py
ipyregulartable/_version.py
ipyregulartable/widget.py
ipyregulartable/datamodel/__init__.py
ipyregulartable/datamodel/base.py
ipyregulartable/datamodel/demo.py
ipyregulartable/datamodel/numpy.py
ipyregulartable/datamodel/pandas.py
ipyregulartable/extension/ipyregulartable.json
ipyregulartable/labextension/package.json
ipyregulartable/labextension/static/308.9eab99760ca6a29ae6c9.js
ipyregulartable/labextension/static/308.9eab99760ca6a29ae6c9.js.LICENSE.txt
ipyregulartable/labextension/static/367.a4a04bf314edcc0d0c6b.js
ipyregulartable/labextension/static/42.67fdb904448f9edf2647.js
ipyregulartable/labextension/static/480.623ca1a19db1a252a051.js
ipyregulartable/labextension/static/568.e54e0e1dd72d24a5f6df.js
ipyregulartable/labextension/static/722.e751c19c667ef93e8352.js
ipyregulartable/labextension/static/790.4673a54c02886e5048c4.js
ipyregulartable/labextension/static/790.4673a54c02886e5048c4.js.LICENSE.txt
ipyregulartable/labextension/static/remoteEntry.ea82ff820da432256317.js
ipyregulartable/labextension/static/style.js
ipyregulartable/labextension/static/third-party-licenses.json
ipyregulartable/nbextension/__init__.py
ipyregulartable/nbextension/static/extension.js
ipyregulartable/nbextension/static/index.js
ipyregulartable/nbextension/static/index.js.LICENSE.txt
ipyregulartable/nbextension/static/index.js.map
ipyregulartable/tests/__init__.py
ipyregulartable/tests/conftest.py
ipyregulartable/tests/test_nbextension_path.py
ipyregulartable-0.2.1.data/data/etc/jupyter/nbconfig/notebook.d/ipyregulartable.json
ipyregulartable-0.2.1.data/data/share/jupyter/labextensions/ipyregulartable/package.json
ipyregulartable-0.2.1.data/data/share/jupyter/labextensions/ipyregulartable/static/308.9eab99760ca6a29ae6c9.js
ipyregulartable-0.2.1.data/data/share/jupyter/labextensions/ipyregulartable/static/308.9eab99760ca6a29ae6c9.js.LICENSE.txt
ipyregulartable-0.2.1.data/data/share/jupyter/labextensions/ipyregulartable/static/367.a4a04bf314edcc0d0c6b.js
ipyregulartable-0.2.1.dist-info/AUTHORS
ipyregulartable-0.2.1.dist-info/LICENSE
ipyregulartable-0.2.1.dist-info/METADATA
ipyregulartable-0.2.1.dist-info/WHEEL
ipyregulartable-0.2.1.dist-info/top_level.txt
ipyregulartable-0.2.1.dist-info/RECORD
