Metadata-Version: 2.1
Name: ipyregulartable
Version: 0.2.1
Summary: ipywidgets wrapper around regular-table
Home-page: https://github.com/jpmorganchase/ipyregulartable
Author: Tim Paine
Author-email: t.paine154@gmail.com
License: Apache 2.0
Keywords: Jupyter,Jupyterlab,Widgets,IPython,Table,Grid,Datagrid
Platform: Linux
Platform: Mac OS X
Platform: Windows
Classifier: Development Status :: 4 - Beta
Classifier: Programming Language :: Python :: 3
Classifier: Programming Language :: Python :: 3.7
Classifier: Programming Language :: Python :: 3.8
Classifier: Programming Language :: Python :: 3.9
Classifier: Programming Language :: Python :: 3.10
Classifier: Framework :: Jupyter
Classifier: Framework :: Jupyter :: JupyterLab
Requires-Python: >=3.7
License-File: LICENSE
License-File: AUTHORS
Requires-Dist: ipywidgets (>=7.5.1)
Requires-Dist: numpy
Requires-Dist: pandas (>=0.22)
Provides-Extra: dev
Requires-Dist: ipywidgets (>=7.5.1) ; extra == 'dev'
Requires-Dist: numpy ; extra == 'dev'
Requires-Dist: pandas (>=0.22) ; extra == 'dev'
Requires-Dist: black (>=20.8b1) ; extra == 'dev'
Requires-Dist: bump2version (>=1.0.0) ; extra == 'dev'
Requires-Dist: check-manifest ; extra == 'dev'
Requires-Dist: flake8 (>=3.7.8) ; extra == 'dev'
Requires-Dist: flake8-black (>=0.2.1) ; extra == 'dev'
Requires-Dist: jupyter-packaging ; extra == 'dev'
Requires-Dist: mock ; extra == 'dev'
Requires-Dist: pytest (>=4.3.0) ; extra == 'dev'
Requires-Dist: pytest-cov (>=2.6.1) ; extra == 'dev'
Requires-Dist: Sphinx (>=1.8.4) ; extra == 'dev'
Requires-Dist: sphinx-markdown-builder (>=0.5.2) ; extra == 'dev'
Provides-Extra: develop
Requires-Dist: ipywidgets (>=7.5.1) ; extra == 'develop'
Requires-Dist: numpy ; extra == 'develop'
Requires-Dist: pandas (>=0.22) ; extra == 'develop'
Requires-Dist: black (>=20.8b1) ; extra == 'develop'
Requires-Dist: bump2version (>=1.0.0) ; extra == 'develop'
Requires-Dist: check-manifest ; extra == 'develop'
Requires-Dist: flake8 (>=3.7.8) ; extra == 'develop'
Requires-Dist: flake8-black (>=0.2.1) ; extra == 'develop'
Requires-Dist: jupyter-packaging ; extra == 'develop'
Requires-Dist: mock ; extra == 'develop'
Requires-Dist: pytest (>=4.3.0) ; extra == 'develop'
Requires-Dist: pytest-cov (>=2.6.1) ; extra == 'develop'
Requires-Dist: Sphinx (>=1.8.4) ; extra == 'develop'
Requires-Dist: sphinx-markdown-builder (>=0.5.2) ; extra == 'develop'
